Workbook

Sheet Data
A1: date | B1: channel | C1: campaign_name | D1: impressions | E1: clicks | F1: conversions | G1: cost | H1: revenue
A2: 45292 | B2: Google Search | C2: Google Search Campaign | D2: 20795 | E2: 1591 | F2: 183 | G2: 3844.46 | H2: 10460.66
A3: 45292 | B3: Meta Ads | C3: Meta Ads Campaign | D3: 21850 | E3: 371 | F3: 29 | G3: 631.08 | H3: 1615.75
A4: 45292 | B4: Email | C4: Email Campaign | D4: 6685 | E4: 93 | F4: 10 | G4: 310.07 | H4: 400.86
A5: 45292 | B5: Display | C5: Display Campaign | D5: 22568 | E5: 706 | F5: 62 | G5: 1388.17 | H5: 4466.18
A6: 45292 | B6: LinkedIn Ads | C6: LinkedIn Ads Campaign | D6: 30658 | E6: 1164 | F6: 30 | G6: 3991.52 | H6: 1968.15
A7: 45293 | B7: Google Search | C7: Google Search Campaign | D7: 24118 | E7: 1285 | F7: 89 | G7: 4439.32 | H7: 8129.61
A8: 45293 | B8: Meta Ads | C8: Meta Ads Campaign | D8: 8556 | E8: 449 | F8: 18 | G8: 438.06 | H8: 2598.79
A9: 45293 | B9: Email | C9: Email Campaign | D9: 13433 | E9: 496 | F9: 10 | G9: 706.01 | H9: 665.13
A10: 45293 | B10: Display | C10: Display Campaign | D10: 28483 | E10: 528 | F10: 44 | G10: 471.42 | H10: 6161.11
A11: 45293 | B11: LinkedIn Ads | C11: LinkedIn Ads Campaign | D11: 31531 | E11: 717 | F11: 84 | G11: 1396.66 | H11: 5281.38
A12: 45294 | B12: Google Search | C12: Google Search Campaign | D12: 14692 | E12: 1144 | F12: 138 | G12: 3817.12 | H12: 19103.48
A13: 45294 | B13: Meta Ads | C13: Meta Ads Campaign | D13: 37606 | E13: 2802 | F13: 88 | G13: 3724.29 | H13: 3957.8
... A601: 45411 | B601: LinkedIn Ads | C601: LinkedIn Ads Campaign | D601: 32128 | E601: 1134 | F601: 162 | G601: 2842.75 | H601: 8795.56

Sheet kpi_summary
A1: channel | B1: impressions | C1: clicks | D1: conversions | E1: cost | F1: revenue | G1: CTR | H1: CVR | I1: CAC | J1: ROAS | K1: Profit | L1: Profit_Margin | M1: Efficiency_Tag | N1: Action
A2: Google Search | B2: =SUMIFS(tblMarketing[impressions], tblMarketing[channel], $A2) -> 2834299 | C2: =SUMIFS(tblMarketing[clicks], tblMarketing[channel], $A2) -> 129224 | D2: =SUMIFS(tblMarketing[conversions], tblMarketing[channel], $A2) -> 11297 | E2: =SUMIFS(tblMarketing[cost], tblMarketing[channel], $A2) -> 292757.28 | F2: =SUMIFS(tblMarketing[revenue], tblMarketing[channel], $A2) -> 1076106.5 | G2: =IFERROR(C2/B2,0) -> 0.045592931 | H2: =IFERROR(D2/C2,0) -> 0.087421841 | I2: =IFERROR(E2/D2,0) -> 25.914604 | J2: =IFERROR(F2/E2,0) -> 3.6757635 | K2: =F2-E2 -> 783349.25 | L2: =IFERROR(K2/F2,0) -> 0.72794768 | M2: =IF(J2>=3.8,"Winner",IF(J2>=3.4,"Neutral","Waste")) -> Neutral | N2: =IF(M2="Winner","Increase budget",IF(M2="Neutral","Test & optimize","Reduce/Stop spend")) -> Test & optimize
A3: Meta Ads | B3: =SUMIFS(tblMarketing[impressions], tblMarketing[channel], $A3) -> 2610776 | C3: =SUMIFS(tblMarketing[clicks], tblMarketing[channel], $A3) -> 112661 | D3: =SUMIFS(tblMarketing[conversions], tblMarketing[channel], $A3) -> 9342 | E3: =SUMIFS(tblMarketing[cost], tblMarketing[channel], $A3) -> 222058.23 | F3: =SUMIFS(tblMarketing[revenue], tblMarketing[channel], $A3) -> 859194.97 | G3: =IFERROR(C3/B3,0) -> 0.043152304 | H3: =IFERROR(D3/C3,0) -> 0.08292133 | I3: =IFERROR(E3/D3,0) -> 23.769881 | J3: =IFERROR(F3/E3,0) -> 3.8692327 | K3: =F3-E3 -> 637136.74 | L3: =IFERROR(K3/F3,0) -> 0.74155083 | M3: =IF(J3>=3.8,"Winner",IF(J3>=3.4,"Neutral","Waste")) -> Winner | N3: =IF(M3="Winner","Increase budget",IF(M3="Neutral","Test & optimize","Reduce/Stop spend")) -> Increase budget
A4: Email | B4: =SUMIFS(tblMarketing[impressions], tblMarketing[channel], $A4) -> 2721297 | C4: =SUMIFS(tblMarketing[clicks], tblMarketing[channel], $A4) -> 122834 | D4: =SUMIFS(tblMarketing[conversions], tblMarketing[channel], $A4) -> 11312 | E4: =SUMIFS(tblMarketing[cost], tblMarketing[channel], $A4) -> 261204.63 | F4: =SUMIFS(tblMarketing[revenue], tblMarketing[channel], $A4) -> 1108327.8 | G4: =IFERROR(C4/B4,0) -> 0.045138035 | H4: =IFERROR(D4/C4,0) -> 0.092091766 | I4: =IFERROR(E4/D4,0) -> 23.090933 | J4: =IFERROR(F4/E4,0) -> 4.2431398 | K4: =F4-E4 -> 847123.14 | L4: =IFERROR(K4/F4,0) -> 0.76432547 | M4: =IF(J4>=3.8,"Winner",IF(J4>=3.4,"Neutral","Waste")) -> Winner | N4: =IF(M4="Winner","Increase budget",IF(M4="Neutral","Test & optimize","Reduce/Stop spend")) -> Increase budget
A5: Display | B5: =SUMIFS(tblMarketing[impressions], tblMarketing[channel], $A5) -> 2702753 | C5: =SUMIFS(tblMarketing[clicks], tblMarketing[channel], $A5) -> 121145 | D5: =SUMIFS(tblMarketing[conversions], tblMarketing[channel], $A5) -> 11201 | E5: =SUMIFS(tblMarketing[cost], tblMarketing[channel], $A5) -> 276704.79 | F5: =SUMIFS(tblMarketing[revenue], tblMarketing[channel], $A5) -> 1026339.2 | G5: =IFERROR(C5/B5,0) -> 0.044822816 | H5: =IFERROR(D5/C5,0) -> 0.092459449 | I5: =IFERROR(E5/D5,0) -> 24.703579 | J5: =IFERROR(F5/E5,0) -> 3.7091485 | K5: =F5-E5 -> 749634.37 | L5: =IFERROR(K5/F5,0) -> 0.73039634 | M5: =IF(J5>=3.8,"Winner",IF(J5>=3.4,"Neutral","Waste")) -> Neutral | N5: =IF(M5="Winner","Increase budget",IF(M5="Neutral","Test & optimize","Reduce/Stop spend")) -> Test & optimize
A6: LinkedIn Ads | B6: =SUMIFS(tblMarketing[impressions], tblMarketing[channel], $A6) -> 2852560 | C6: =SUMIFS(tblMarketing[clicks], tblMarketing[channel], $A6) -> 131654 | D6: =SUMIFS(tblMarketing[conversions], tblMarketing[channel], $A6) -> 11066 | E6: =SUMIFS(tblMarketing[cost], tblMarketing[channel], $A6) -> 272205.71 | F6: =SUMIFS(tblMarketing[revenue], tblMarketing[channel], $A6) -> 1010746.8 | G6: =IFERROR(C6/B6,0) -> 0.046152929 | H6: =IFERROR(D6/C6,0) -> 0.084053656 | I6: =IFERROR(E6/D6,0) -> 24.598383 | J6: =IFERROR(F6/E6,0) -> 3.7131725 | K6: =F6-E6 -> 738541.04 | L6: =IFERROR(K6/F6,0) -> 0.73068851 | M6: =IF(J6>=3.8,"Winner",IF(J6>=3.4,"Neutral","Waste")) -> Neutral | N6: =IF(M6="Winner","Increase budget",IF(M6="Neutral","Test & optimize","Reduce/Stop spend")) -> Test & optimize

Sheet budget_scenario
A1: channel | B1: current_cost | C1: scenario_cost | D1: scenario_revenue | E1: scenario_profit | F1: scenario_ROAs | G1: delta_cost | H1: delta_profit | I1: current_profit
A2: Email | B2: =INDEX(kpi_summary!$E$2:$E$6, MATCH($A2, kpi_summary!$A$2:$A$6, 0)) -> 261204.63 | C2: =IF( INDEX(kpi_summary!$M$2:$M$6,MATCH($A2,kpi_summary!$A$2:$A$6,0))="Neutral", B2*(1-0.1), IF( INDEX(kpi_summary!$M$2:$M$6,MATCH($A2,kpi_summary!$A$2:$A$6,0))="Winner", B2 + ($L$4/$L$3), B2 ) ) -> 303288.02 | D2: =C2*INDEX(kpi_summary!$J$2:$J$6,MATCH($A2,kpi_summary!$A$2:$A$6,0)) -> 1286893.5 | E2: =D2-C2 -> 983605.46 | F2: =IFERROR(D2/C2,0) -> 4.2431398 | G2: =C2-B2 -> 42083.389 | H2: =E2-(INDEX(kpi_summary!$K$2:$K$6,MATCH($A2,kpi_summary!$A$2:$A$6,0))) -> 136482.32 | I2: =INDEX(kpi_summary!$K$2:$K$6,MATCH($A2,kpi_summary!$A$2:$A$6,0)) -> 847123.14 | K2: Neutral_Spend | L2: =SUMIF(kpi_summary!$M$2:$M$6,"Neutral",kpi_summary!$E$2:$E$6) -> 841667.78
A3: Meta Ads | B3: =INDEX(kpi_summary!$E$2:$E$6, MATCH($A3, kpi_summary!$A$2:$A$6, 0)) -> 222058.23 | C3: =IF( INDEX(kpi_summary!$M$2:$M$6,MATCH($A3,kpi_summary!$A$2:$A$6,0))="Neutral", B3*(1-0.1), IF( INDEX(kpi_summary!$M$2:$M$6,MATCH($A3,kpi_summary!$A$2:$A$6,0))="Winner", B3 + ($L$4/$L$3), B3 ) ) -> 264141.62 | D3: =C3*INDEX(kpi_summary!$J$2:$J$6,MATCH($A3,kpi_summary!$A$2:$A$6,0)) -> 1022025.4 | E3: =D3-C3 -> 757883.78 | F3: =IFERROR(D3/C3,0) -> 3.8692327 | G3: =C3-B3 -> 42083.389 | H3: =E3-(INDEX(kpi_summary!$K$2:$K$6,MATCH($A3,kpi_summary!$A$2:$A$6,0))) -> 120747.04 | I3: =INDEX(kpi_summary!$K$2:$K$6,MATCH($A3,kpi_summary!$A$2:$A$6,0)) -> 637136.74 | K3: Winner_Count | L3: =COUNTIF(kpi_summary!$M$2:$M$6,"Winner") -> 2
A4: Google Search | B4: =INDEX(kpi_summary!$E$2:$E$6, MATCH($A4, kpi_summary!$A$2:$A$6, 0)) -> 292757.28 | C4: =IF( INDEX(kpi_summary!$M$2:$M$6,MATCH($A4,kpi_summary!$A$2:$A$6,0))="Neutral", B4*(1-0.1), IF( INDEX(kpi_summary!$M$2:$M$6,MATCH($A4,kpi_summary!$A$2:$A$6,0))="Winner", B4 + ($L$4/$L$3), B4 ) ) -> 263481.55 | D4: =C4*INDEX(kpi_summary!$J$2:$J$6,MATCH($A4,kpi_summary!$A$2:$A$6,0)) -> 968495.88 | E4: =D4-C4 -> 705014.32 | F4: =IFERROR(D4/C4,0) -> 3.6757635 | G4: =C4-B4 -> -29275.728 | H4: =E4-(INDEX(kpi_summary!$K$2:$K$6,MATCH($A4,kpi_summary!$A$2:$A$6,0))) -> -78334.925 | I4: =INDEX(kpi_summary!$K$2:$K$6,MATCH($A4,kpi_summary!$A$2:$A$6,0)) -> 783349.25 | K4: Realloc_Pool (20% of waste spend) | L4: =0.1*L2 -> 84166.778
A5: Display | B5: =INDEX(kpi_summary!$E$2:$E$6, MATCH($A5, kpi_summary!$A$2:$A$6, 0)) -> 276704.79 | C5: =IF( INDEX(kpi_summary!$M$2:$M$6,MATCH($A5,kpi_summary!$A$2:$A$6,0))="Neutral", B5*(1-0.1), IF( INDEX(kpi_summary!$M$2:$M$6,MATCH($A5,kpi_summary!$A$2:$A$6,0))="Winner", B5 + ($L$4/$L$3), B5 ) ) -> 249034.31 | D5: =C5*INDEX(kpi_summary!$J$2:$J$6,MATCH($A5,kpi_summary!$A$2:$A$6,0)) -> 923705.24 | E5: =D5-C5 -> 674670.93 | F5: =IFERROR(D5/C5,0) -> 3.7091485 | G5: =C5-B5 -> -27670.479 | H5: =E5-(INDEX(kpi_summary!$K$2:$K$6,MATCH($A5,kpi_summary!$A$2:$A$6,0))) -> -74963.437 | I5: =INDEX(kpi_summary!$K$2:$K$6,MATCH($A5,kpi_summary!$A$2:$A$6,0)) -> 749634.37
A6: LinkedIn Ads | B6: =INDEX(kpi_summary!$E$2:$E$6, MATCH($A6, kpi_summary!$A$2:$A$6, 0)) -> 272205.71 | C6: =IF( INDEX(kpi_summary!$M$2:$M$6,MATCH($A6,kpi_summary!$A$2:$A$6,0))="Neutral", B6*(1-0.1), IF( INDEX(kpi_summary!$M$2:$M$6,MATCH($A6,kpi_summary!$A$2:$A$6,0))="Winner", B6 + ($L$4/$L$3), B6 ) ) -> 244985.14 | D6: =C6*INDEX(kpi_summary!$J$2:$J$6,MATCH($A6,kpi_summary!$A$2:$A$6,0)) -> 909672.08 | E6: =D6-C6 -> 664686.94 | F6: =IFERROR(D6/C6,0) -> 3.7131725 | G6: =C6-B6 -> -27220.571 | H6: =E6-(INDEX(kpi_summary!$K$2:$K$6,MATCH($A6,kpi_summary!$A$2:$A$6,0))) -> -73854.104 | I6: =INDEX(kpi_summary!$K$2:$K$6,MATCH($A6,kpi_summary!$A$2:$A$6,0)) -> 738541.04
B8: =SUM(B2:B6) = SUM(C2:C6) -> TRUE
